hlpl/__init__.py
hlpl/__main__.py
hlpl/setup.cfg
hlpl-1.0.15.dist-info/LICENSE
hlpl-1.0.15.dist-info/METADATA
hlpl-1.0.15.dist-info/WHEEL
hlpl-1.0.15.dist-info/entry_points.txt
hlpl-1.0.15.dist-info/top_level.txt
hlpl-1.0.15.dist-info/RECORD
