Metadata-Version: 2.1
Name: hlpl
Version: 1.0.15
Summary: A Programming Language for Human Life 
Home-page: https://hlpl.net
Author: Ahmida Bendjoudi
Author-email: email@hlpl.com
License: MIT
Download-URL: https://hlpl.net/download/
Project-URL: hlpl_composer, https://composer.hlpl.net
Project-URL: hlpl_templater, https://templater.hlpl.net
Project-URL: hlpl_transcriber, https://transcriber.hlpl.net
Project-URL: hlpl_press, https://press.hlpl.net
Project-URL: hlpl_character, https://character.hlpl.net
Project-URL: hlpl_photographer, https://photographer.hlpl.net
Project-URL: hlpl_graphics, https://graphics.hlpl.net
Project-URL: hlpl_docs, https://docs.hlpl.net
Project-URL: hlpl_forum, https://forum.hlpl.net
Project-URL: hlpl_resource, https://graphics.hlpl.net
Keywords: hlpl,hlpl docs,hlpl composer,hlpl templater,hlpl transcriber,hlpl press,hlpl character,hlpl photographer,hlpl graphis,human life programming language
Platform: UNKNOWN
Classifier: Framework :: Robot Framework
Classifier: Framework :: Robot Framework :: Library
Classifier: Framework :: Robot Framework :: Tool
Classifier: Natural Language :: Arabic
Classifier: Natural Language :: English
Requires-Python: >=3, <=3.9
Requires-Dist: hlpl-graphics
Requires-Dist: hlpl-photographer
Requires-Dist: hlpl-character
Requires-Dist: hlpl-press
Requires-Dist: hlpl-transcriber
Requires-Dist: hlpl-templater
Requires-Dist: hlpl-composer
